<?xml version="1.0" encoding="ISO-8859-1"?>
<afc xmlns="http://www.mscsoftware.com/:vfc" xmlns:afc="http://www.mscsoftware.com/:afc">
     <afc:Bibliography>
          <File schema="afc" version="2.0.0.0" URI="mdids://SCG007C_R01/springs.tbl/SUSP_REAR_SCG007C_V09_iss1_spring.xml" publicationDate="2020-10-26 16:07:53+01:00"/>
          <Revision version="17.0"/>
          <Corporation author="MSC.Software" URI="http://www.mscsoftware.com/"/>
          <Author user="Stefano.Rapisarda" name="-unknown name-"/>
          <Environment hostName="PE-NTBK-047" operatingSystem="MS Windows NT 6.2"/>
          <Application name="MSC/AFC" version="02.00.00"/>
     </afc:Bibliography>
     <afc:Units>
          <afc:UnitSetting name="angle" current="deg"/>
          <afc:UnitSetting name="current" current="ampere"/>
          <afc:UnitSetting name="force" current="newton"/>
          <afc:UnitSetting name="length" current="mm"/>
          <afc:UnitSetting name="luminosity" current="candela"/>
          <afc:UnitSetting name="mass" current="kg"/>
          <afc:UnitSetting name="quantity" current="mole"/>
          <afc:UnitSetting name="solidAngle" current="steradian"/>
          <afc:UnitSetting name="temperature" current="kelvin"/>
          <afc:UnitSetting name="time" current="sec"/>
          <afc:UnitSetting name="frequency" current="Hz"/>
     </afc:Units>
     <SpringProperties name="spring" active="true" userDefined="false" diameter="1" coils="5" rate="148" freeLength="152" method="linear" independentAxis="deflection">
          <Spline name="spline_data" id="0" active="true" userDefined="false" interpolation_method="akima" yLabel="Spring Force" xUnit="length" yUnit="force" datablock="Spring Force">
            <![CDATA[
       -32.2741        -3227.41
       -24.1052        -2410.52
       -16.0309        -1603.09
       -8.00676        -800.676
              0               0
        8.01441         801.441
         16.056          1605.6
        24.1399         2413.99
        32.2772         3227.72
        40.4751         4047.51
         48.736          4873.6
        57.0564         5705.64
]]>
          </Spline>
     </SpringProperties>
</afc>
