<?xml version="1.0" encoding="ISO-8859-1"?>
<afc xmlns="http://www.mscsoftware.com/:vfc" xmlns:afc="http://www.mscsoftware.com/:afc">
     <afc:Bibliography>
          <File schema="afc" version="2.0.0.0" URI="mdids://SCG007C_R01/springs.tbl/SUSP_REAR_SCG004C_R06c_ModFor3rdElem_v3_AL4p_spring.xml" publicationDate="2020-01-08 11:00:51+01:00"/>
          <Revision version="17.0"/>
          <Corporation author="MSC.Software" URI="http://www.mscsoftware.com/"/>
          <Author user="Stefano.Rapisarda" name="-unknown name-"/>
          <Environment hostName="PE-NTBK-007" operatingSystem="MS Windows NT 6.2"/>
          <Application name="MSC/AFC" version="02.00.00"/>
     </afc:Bibliography>
     <afc:Units>
          <afc:UnitSetting name="angle" current="deg"/>
          <afc:UnitSetting name="current" current="ampere"/>
          <afc:UnitSetting name="force" current="newton"/>
          <afc:UnitSetting name="length" current="mm"/>
          <afc:UnitSetting name="luminosity" current="candela"/>
          <afc:UnitSetting name="mass" current="kg"/>
          <afc:UnitSetting name="quantity" current="mole"/>
          <afc:UnitSetting name="solidAngle" current="steradian"/>
          <afc:UnitSetting name="temperature" current="kelvin"/>
          <afc:UnitSetting name="time" current="sec"/>
          <afc:UnitSetting name="frequency" current="Hz"/>
     </afc:Units>
     <SpringProperties name="spring" active="true" userDefined="false" diameter="1" coils="5" rate="130" freeLength="300" method="linear" independentAxis="deflection">
          <Spline name="spline_data" id="0" active="true" userDefined="false" interpolation_method="akima" yLabel="Spring Force" xUnit="length" yUnit="force" datablock="Spring Force">
            <![CDATA[
       -39.8269        -8363.65
       -33.2259        -6977.44
       -26.6123        -5588.59
       -19.9843         -4196.7
       -13.3403        -2801.47
       -6.67915        -1402.62
              0               0
        6.69754         1406.48
        13.4134         2816.82
        20.1472          4230.9
        26.8976         5648.49
        33.6629         7069.21
        40.4405         8492.51
]]>
          </Spline>
     </SpringProperties>
</afc>
